ttal/__init__.py
ttal/core.py
ttal-0.1.3.dist-info/METADATA
ttal-0.1.3.dist-info/WHEEL
ttal-0.1.3.dist-info/top_level.txt
ttal-0.1.3.dist-info/RECORD
