Metadata-Version: 2.4
Name: ttal
Version: 0.1.3
Summary: Torch Tune abstractions for local LLM inference.
Requires-Python: >=3.8
Requires-Dist: torch
Requires-Dist: torchtune
Requires-Dist: huggingface_hub
